graphlan.py
graphlan_annotate.py
setup.py
graphlan.egg-info/PKG-INFO
graphlan.egg-info/SOURCES.txt
graphlan.egg-info/dependency_links.txt
graphlan.egg-info/requires.txt
graphlan.egg-info/top_level.txt
src/__init__.py
src/graphlan_lib.py
src/pyphlan.py