Metadata-Version: 2.1
Name: graphlan
Version: 1.1.3
Summary: GraPhlAn is a software tool for producing high-quality circular representations of taxonomic and phylogenetic trees. GraPhlAn focuses on concise, integrative, informative, and publication-ready representations of phylogenetically- and taxonomically-driven investigation.
Home-page: http://github.com/biobakery/graphlan
Author: Francesco Asnicar
Author-email: f.asnicar@unitn.it
License: UNKNOWN
Platform: UNKNOWN
